offtheface/__init__.py
offtheface/offtheface.py
offtheface-0.1.2.dist-info/LICENSE
offtheface-0.1.2.dist-info/METADATA
offtheface-0.1.2.dist-info/WHEEL
offtheface-0.1.2.dist-info/entry_points.txt
offtheface-0.1.2.dist-info/top_level.txt
offtheface-0.1.2.dist-info/RECORD
