Metadata-Version: 2.1
Name: offtheface
Version: 0.1.2
Summary: justin bieber
Home-page: https://offtheface.github.io/offtheface
Author: offtheface
Author-email: rokany@cau.ac.kr
License: GNU General Public License (GPL)
Project-URL: Bug Tracker, https://github.com/offtheface/offtheface/issues
Platform: macOS
Classifier: Programming Language :: Python :: 3
Classifier: License :: OSI Approved :: GNU General Public License (GPL)
Classifier: Operating System :: OS Independent
Requires-Python: >=3.6
License-File: LICENSE
